caterpie/LICENSE
caterpie/README.md
caterpie/__init__.py
caterpie/postgresql/__init__.py
caterpie/postgresql/postgresql_test.py
caterpie/postgresql/postgresql_utils.py
caterpie/postgresql/postgresql_utils_test.py
caterpie/sqlite/sqlite_utils.py
caterpie/sqlite/sqlite_utils_test.py
caterpie/table.py
caterpie-0.1.0.dist-info/WHEEL
caterpie-0.1.0.dist-info/METADATA
caterpie-0.1.0.dist-info/RECORD
